my_simple_package/__init__.py
my_simple_package/helloWorld.py
my_simple_package-0.0.1.dist-info/LICENSE.txt
my_simple_package-0.0.1.dist-info/METADATA
my_simple_package-0.0.1.dist-info/WHEEL
my_simple_package-0.0.1.dist-info/top_level.txt
my_simple_package-0.0.1.dist-info/RECORD
