Metadata-Version: 2.1
Name: my-simple-package
Version: 0.0.1
Summary: simple test
Author: alon12345
Author-email: alonf1536@gmail.com
License-File: LICENSE.txt
